bqpipe/__init__.py
bqpipe/bigquery.py
bqpipe/core.py
bqpipe/helpers.py
bqpipe/snowflake.py
bqpipe-0.5.2.dist-info/LICENSE
bqpipe-0.5.2.dist-info/METADATA
bqpipe-0.5.2.dist-info/WHEEL
bqpipe-0.5.2.dist-info/top_level.txt
bqpipe-0.5.2.dist-info/RECORD
