Metadata-Version: 2.1
Name: bqpipe
Version: 0.5.2
Summary: Wrapper around BigQuery & Snowflake libraries to simplify writing to/reading from Pandas DataFrames.
Home-page: https://github.com/4mile/BQPipe
Author: Johnathan Brooks
Author-email: jb@4mile.io
License: Type license() to see the full license text
Project-URL: Bug Reports, https://github.com/4mile/BQPipe/issues
Project-URL: Source, https://github.com/4mile/BQPipe
Keywords: bigquery snowflake google cloud etl data engineering dataframe pandas
Platform: UNKNOWN
Classifier: Development Status :: 4 - Beta
Classifier: Intended Audience :: Developers
Classifier: License :: OSI Approved :: Apache Software License
Classifier: Topic :: Database
Classifier: Programming Language :: Python
Classifier: Programming Language :: Python :: 3
Classifier: Programming Language :: Python :: 3.7
Classifier: Programming Language :: Python :: 3.8
Requires-Python: >=3.7, <4
Requires-Dist: numpy
Requires-Dist: pandas
Requires-Dist: google-cloud-bigquery
Requires-Dist: cryptography
Requires-Dist: pyarrow
Requires-Dist: snowflake-connector-python[pandas]
Requires-Dist: snowflake-sqlalchemy
